{"int_low": {"occ": {"5": 2096.0, "17": 2097.0, "50": 2099.0, "83": 2100.0, "95": 2100.0}, "chrnc": {"5": NaN, "17": NaN, "50": NaN, "83": NaN, "95": NaN}, "delta": {"5": NaN, "17": NaN, "50": NaN, "83": NaN, "95": NaN}}, "int": {"occ": {"5": 2060.0, "17": 2062.0, "50": 2067.0, "83": 2073.0, "95": 2074.0}, "chrnc": {"5": 2093.0, "17": 2094.0, "50": 2095.0, "83": 2097.0, "95": 2099.0}, "delta": {"5": 21.0, "17": 23.0, "50": 29.0, "83": 34.0, "95": 36.0}}, "int_high": {"occ": {"5": 2043.0, "17": 2046.0, "50": 2054.0, "83": 2056.0, "95": 2056.0}, "chrnc": {"5": 2072.0, "17": 2073.0, "50": 2074.0, "83": 2075.0, "95": 2076.0}, "delta": {"5": 17.0, "17": 18.0, "50": 20.0, "83": 28.0, "95": 31.0}}, "kopp": {"occ": {"5": 2060.0, "17": 2067.0, "50": 2082.0, "83": 2095.0, "95": 2099.0}, "chrnc": {"5": 2076.0, "17": 2087.0, "50": 2096.0, "83": 2099.0, "95": 2100.0}, "delta": {"5": 16.0, "17": 21.0, "50": 26.0, "83": 33.0, "95": 37.0}}}